dias_scraper/__init__.py
dias_scraper/diasScraper.py
dias_scraper-1.0.0.dist-info/METADATA
dias_scraper-1.0.0.dist-info/WHEEL
dias_scraper-1.0.0.dist-info/entry_points.txt
dias_scraper-1.0.0.dist-info/top_level.txt
dias_scraper-1.0.0.dist-info/RECORD
