Metadata-Version: 2.2
Name: dias-scraper
Version: 1.0.0
Summary: A command line tool to check your grades for Ionian University
Home-page: https://github.com/YGNT7777/Dias-Scraper
Author: YGNT7777
License: MIT
Keywords: Ionian University,Dias Scraper
Requires-Python: >=3.6
Requires-Dist: playwright
Requires-Dist: colorama
Dynamic: author
Dynamic: home-page
Dynamic: keywords
Dynamic: license
Dynamic: requires-dist
Dynamic: requires-python
Dynamic: summary
